convert_and_download/__init__.py
convert_and_download/_version.py
convert_and_download/static/main.js
convert_and_download-0.3.0.data/data/etc/jupyter/jupyter_notebook_config.d/convert_and_download.json
convert_and_download-0.3.0.data/data/etc/jupyter/nbconfig/tree.d/convert_and_download.json
convert_and_download-0.3.0.data/data/share/jupyter/nbextensions/convert_and_download/main.js
convert_and_download-0.3.0.dist-info/LICENSE
convert_and_download-0.3.0.dist-info/METADATA
convert_and_download-0.3.0.dist-info/WHEEL
convert_and_download-0.3.0.dist-info/top_level.txt
convert_and_download-0.3.0.dist-info/RECORD
