Metadata-Version: 2.1
Name: convert-and-download
Version: 0.3.0
Summary: Convert and Download Jupyter Notebooks
Home-page: https://github.com/bryanwweber/convert_and_download
Author: Bryan W. Weber
Author-email: bryan.w.weber@gmail.com
License: BSD-3-Clause
Project-URL: Bug Reports, https://github.com/bryanwweber/convert_and_download/issues
Project-URL: Source, https://github.com/bryanwweber/convert_and_download/
Keywords: jupyter notebook javascript pdf
Platform: UNKNOWN
Classifier: Development Status :: 3 - Alpha
Classifier: Intended Audience :: Developers
Classifier: Topic :: Software Development :: Build Tools
Classifier: License :: OSI Approved :: BSD License
Classifier: Programming Language :: Python :: 3
Classifier: Programming Language :: Python :: 3.6
Classifier: Programming Language :: Python :: 3.7
Requires-Python: ~=3.6
Requires-Dist: thermohw (<1.0,>=0.4)
Requires-Dist: notebook (<7.0,>=5.5.0)
Requires-Dist: ipython-genutils (<1.0,>=0.2.0)
Requires-Dist: pdfrw (<0.5.0,>=0.4.0)
